{
    "netcdf_file": "/home/dadiyorto/freelance/02_ort_ecmwf/station_mapping/EFAS/EFAS/upArea.nc",
    "nc_variable": "Band1",
    "nc_grid_size_arcmin": 1.0,
    "csv_file": "/home/dadiyorto/freelance/02_ort_ecmwf/station_mapping/20231205_outlets.csv",
    "csv_lat_col": "StationLat",
    "csv_lon_col": "StationLon",
    "csv_station_name_col": "StationName",
    "csv_variable": "DrainingArea.km2.Provider",
    "max_neighboring_cells": 5,
    "max_area_diff": 10,
    "min_area_diff": 1,
    "manual_lat_col": "LisfloodX",
    "manual_lon_col": "LisfloodY",
    "manual_area": "DrainingArea.km2.LDD"
}